MANIFEST.in
README.md
setup.py
pyautoweka/__init__.py
pyautoweka/pyautoweka.py
pyautoweka.egg-info/PKG-INFO
pyautoweka.egg-info/SOURCES.txt
pyautoweka.egg-info/dependency_links.txt
pyautoweka.egg-info/eager_resources.txt
pyautoweka.egg-info/top_level.txt
pyautoweka/java/autoweka.jar
pyautoweka/java/weka.jar
pyautoweka/java/params/attribselection/eval/weka.attributeSelection.CfsSubsetEval.params
pyautoweka/java/params/attribselection/eval/weka.attributeSelection.CorrelationAttributeEval.params
pyautoweka/java/params/attribselection/eval/weka.attributeSelection.GainRatioAttributeEval.params
pyautoweka/java/params/attribselection/eval/weka.attributeSelection.InfoGainAttributeEval.params
pyautoweka/java/params/attribselection/eval/weka.attributeSelection.OneRAttributeEval.params
pyautoweka/java/params/attribselection/eval/weka.attributeSelection.PrincipalComponents.params
pyautoweka/java/params/attribselection/eval/weka.attributeSelection.ReliefFAttributeEval.params
pyautoweka/java/params/attribselection/eval/weka.attributeSelection.SymmetricalUncertAttributeEval.params
pyautoweka/java/params/attribselection/search/weka.attributeSelection.BestFirst.params
pyautoweka/java/params/attribselection/search/weka.attributeSelection.GreedyStepwise.params
pyautoweka/java/params/attribselection/search/weka.attributeSelection.Ranker.params
pyautoweka/java/params/base/weka.classifiers.bayes.BayesNet.params
pyautoweka/java/params/base/weka.classifiers.bayes.NaiveBayes.params
pyautoweka/java/params/base/weka.classifiers.bayes.NaiveBayesMultinomial.params
pyautoweka/java/params/base/weka.classifiers.functions.GaussianProcesses.params
pyautoweka/java/params/base/weka.classifiers.functions.LinearRegression.params
pyautoweka/java/params/base/weka.classifiers.functions.Logistic.params
pyautoweka/java/params/base/weka.classifiers.functions.MultilayerPerceptron.params
pyautoweka/java/params/base/weka.classifiers.functions.SGD.params
pyautoweka/java/params/base/weka.classifiers.functions.SMO.params
pyautoweka/java/params/base/weka.classifiers.functions.SMOreg.params
pyautoweka/java/params/base/weka.classifiers.functions.SimpleLinearRegression.params
