Metadata-Version: 1.1
Name: pyautoweka
Version: 1.1
Summary: AutoWeka for python
Home-page: http://www.cs.ubc.ca/labs/beta/Projects/autoweka/
Author: Tobias Domhan
Author-email: tdomhan@gmail.com
License: UNKNOWN
Platform: UNKNOWN
Requires: lxml
Requires: numpy
